Metadata-Version: 1.1
Name: libcorepy
Version: 0.0.7
Summary: Library based on the gocore libcore library
Home-page: https://github.com/rafael180496/LIBCOREPY
Author: Rafael Antonio Hidalgo
Author-email: rafael180496@gmail.com
License: MIT
Download-URL: https://github.com/rafael180496/LIBCOREPY/tarball/v0.0.1
Platform: UNKNOWN
Classifier: Programming Language :: Python :: 3.3
Classifier: Programming Language :: Python :: 3.4
Classifier: Programming Language :: Python :: 3.5
Classifier: Programming Language :: Python :: 3.6
Classifier: Programming Language :: Python :: 3.7
